{
    "key": "group_5a5877b297dab",
    "title": "Sponsors",
    "fields": [
        {
            "key": "field_5a5877ceefe3c",
            "label": "Enlace",
            "name": "sponsor_link",
            "type": "url",
            "instructions": "",
            "required": 0,
            "conditional_logic": 0,
            "wrapper": {
                "width": "",
                "class": "",
                "id": ""
            },
            "default_value": "",
            "placeholder": ""
        },
        {
            "key": "field_5a8edad9de1d6",
            "label": "Logo footer",
            "name": "sponsor_alt_logo",
            "type": "image",
            "instructions": "Los logos de los sponsors se muestran a la mitad del tamaño al que se suben.",
            "required": 0,
            "conditional_logic": 0,
            "wrapper": {
                "width": "",
                "class": "",
                "id": ""
            },
            "return_format": "id",
            "preview_size": "thumbnail",
            "library": "all",
            "min_width": "",
            "min_height": "",
            "min_size": "",
            "max_width": "",
            "max_height": "",
            "max_size": "",
            "mime_types": ""
        },
        {
            "key": "field_5a5877e1efe3d",
            "label": "Tipo",
            "name": "sponsor_type",
            "type": "select",
            "instructions": "",
            "required": 0,
            "conditional_logic": 0,
            "wrapper": {
                "width": "",
                "class": "",
                "id": ""
            },
            "choices": {
                "0": "Principal",
                "gold": "Gold",
                "silver": "Silver",
                "bronze": "Bronze",
                "2": "Contributors"
            },
            "default_value": false,
            "allow_null": 0,
            "multiple": 0,
            "ui": 0,
            "return_format": "value",
            "ajax": 0,
            "placeholder": ""
        },
        {
            "key": "field_5a8edafcde1d7",
            "label": "Twitter",
            "name": "sponsor_twitter",
            "type": "link",
            "instructions": "",
            "required": 0,
            "conditional_logic": [
                [
                    {
                        "field": "field_5a5877e1efe3d",
                        "operator": "==",
                        "value": "0"
                    }
                ],
                [
                    {
                        "field": "field_5a5877e1efe3d",
                        "operator": "==",
                        "value": "gold"
                    }
                ]
            ],
            "wrapper": {
                "width": "",
                "class": "",
                "id": ""
            },
            "return_format": "array"
        },
        {
            "key": "field_5a8edb2dde1d8",
            "label": "Facebook",
            "name": "sponsor_facebook",
            "type": "link",
            "instructions": "",
            "required": 0,
            "conditional_logic": [
                [
                    {
                        "field": "field_5a5877e1efe3d",
                        "operator": "==",
                        "value": "0"
                    }
                ],
                [
                    {
                        "field": "field_5a5877e1efe3d",
                        "operator": "==",
                        "value": "gold"
                    }
                ]
            ],
            "wrapper": {
                "width": "",
                "class": "",
                "id": ""
            },
            "return_format": "array"
        },
        {
            "key": "field_5a8edb37de1d9",
            "label": "Youtube",
            "name": "sponsor_youtube",
            "type": "link",
            "instructions": "",
            "required": 0,
            "conditional_logic": [
                [
                    {
                        "field": "field_5a5877e1efe3d",
                        "operator": "==",
                        "value": "0"
                    }
                ],
                [
                    {
                        "field": "field_5a5877e1efe3d",
                        "operator": "==",
                        "value": "gold"
                    }
                ]
            ],
            "wrapper": {
                "width": "",
                "class": "",
                "id": ""
            },
            "return_format": "array"
        },
        {
            "key": "field_5a8edb41de1da",
            "label": "Instagram",
            "name": "sponsor_instagram",
            "type": "link",
            "instructions": "",
            "required": 0,
            "conditional_logic": [
                [
                    {
                        "field": "field_5a5877e1efe3d",
                        "operator": "==",
                        "value": "0"
                    }
                ],
                [
                    {
                        "field": "field_5a5877e1efe3d",
                        "operator": "==",
                        "value": "gold"
                    }
                ]
            ],
            "wrapper": {
                "width": "",
                "class": "",
                "id": ""
            },
            "return_format": "array"
        },
        {
            "key": "field_5fe3398e454b0",
            "label": "Descripción Español",
            "name": "text_es",
            "type": "textarea",
            "instructions": "",
            "required": 0,
            "conditional_logic": [
                [
                    {
                        "field": "field_5a5877e1efe3d",
                        "operator": "==",
                        "value": "0"
                    }
                ],
                [
                    {
                        "field": "field_5a5877e1efe3d",
                        "operator": "==",
                        "value": "gold"
                    }
                ]
            ],
            "wrapper": {
                "width": "",
                "class": "",
                "id": ""
            },
            "default_value": "",
            "placeholder": "",
            "maxlength": "",
            "rows": "",
            "new_lines": "wpautop"
        },
        {
            "key": "field_5fec7191548aa",
            "label": "Descripción Inglés",
            "name": "text_en",
            "type": "textarea",
            "instructions": "",
            "required": 0,
            "conditional_logic": [
                [
                    {
                        "field": "field_5a5877e1efe3d",
                        "operator": "==",
                        "value": "0"
                    }
                ],
                [
                    {
                        "field": "field_5a5877e1efe3d",
                        "operator": "==",
                        "value": "gold"
                    }
                ]
            ],
            "wrapper": {
                "width": "",
                "class": "",
                "id": ""
            },
            "default_value": "",
            "placeholder": "",
            "maxlength": "",
            "rows": "",
            "new_lines": "wpautop"
        },
        {
            "key": "field_5fec71a2548ac",
            "label": "Descripción Italiano",
            "name": "text_it",
            "type": "textarea",
            "instructions": "",
            "required": 0,
            "conditional_logic": [
                [
                    {
                        "field": "field_5a5877e1efe3d",
                        "operator": "==",
                        "value": "0"
                    }
                ],
                [
                    {
                        "field": "field_5a5877e1efe3d",
                        "operator": "==",
                        "value": "gold"
                    }
                ]
            ],
            "wrapper": {
                "width": "",
                "class": "",
                "id": ""
            },
            "default_value": "",
            "placeholder": "",
            "maxlength": "",
            "rows": "",
            "new_lines": "wpautop"
        }
    ],
    "location": [
        [
            {
                "param": "post_type",
                "operator": "==",
                "value": "sponsor"
            }
        ]
    ],
    "menu_order": 0,
    "position": "normal",
    "style": "default",
    "label_placement": "top",
    "instruction_placement": "label",
    "hide_on_screen": [
        "permalink",
        "the_content",
        "excerpt",
        "discussion",
        "comments",
        "revisions",
        "slug",
        "author",
        "format",
        "page_attributes",
        "categories",
        "tags",
        "send-trackbacks"
    ],
    "active": true,
    "description": "",
    "modified": 1609331124
}